typecraft/__init__.py
typecraft/converting.py
typecraft/extras/__init__.py
typecraft/extras/toml.py
typecraft/extras/yaml.py
typecraft/inspecting/__init__.py
typecraft/inspecting/annotations.py
typecraft/inspecting/classes.py
typecraft/inspecting/functions.py
typecraft/models.py
typecraft/serializing.py
typecraft/typedefs.py
typecraft/utils/__init__.py
typecraft/utils/object_collections.py
typecraft/validating.py
typecraft-0.1.0.dist-info/LICENSE
typecraft-0.1.0.dist-info/METADATA
typecraft-0.1.0.dist-info/WHEEL
typecraft-0.1.0.dist-info/RECORD
