Metadata-Version: 2.3
Name: typecraft
Version: 0.1.0
Summary: Annotation-native toolkit for data validation, transformation, and type inspection
Author: mm21
Author-email: mm21.dev@gmail.com
Requires-Python: >=3.12,<4.0
Classifier: Development Status :: 3 - Alpha
Classifier: License :: OSI Approved :: MIT License
Classifier: Natural Language :: English
Classifier: Operating System :: OS Independent
Classifier: Programming Language :: Python :: 3
Classifier: Programming Language :: Python :: 3.12
Classifier: Programming Language :: Python :: 3.13
Classifier: Programming Language :: Python :: Implementation :: CPython
Classifier: Topic :: Software Development :: Libraries :: Python Modules
Classifier: Typing :: Typed
Provides-Extra: toml
Requires-Dist: tomlkit (>=0.13.3,<0.14.0) ; extra == "toml"
Project-URL: Homepage, https://github.com/mm21/typecraft
